pyxel_config_lab_bridge/__init__.py
pyxel_config_lab_bridge/pyxel_config_lab_bridge.py
pyxel_config_lab_bridge/labextension/build_log.json
pyxel_config_lab_bridge/labextension/package.json
pyxel_config_lab_bridge/labextension/schemas/pyxel-config-lab/index.ts
pyxel_config_lab_bridge/labextension/schemas/pyxel-config-lab/package.json.orig
pyxel_config_lab_bridge/labextension/static/lib_index_js.2803555c8a46e24256df.js
pyxel_config_lab_bridge/labextension/static/lib_index_js.2803555c8a46e24256df.js.map
pyxel_config_lab_bridge/labextension/static/remoteEntry.1e8d6ea884297732f103.js
pyxel_config_lab_bridge/labextension/static/remoteEntry.1e8d6ea884297732f103.js.map
pyxel_config_lab_bridge/labextension/static/style.js
pyxel_config_lab_bridge-0.2.2.dist-info/METADATA
pyxel_config_lab_bridge-0.2.2.dist-info/WHEEL
pyxel_config_lab_bridge-0.2.2.dist-info/entry_points.txt
pyxel_config_lab_bridge-0.2.2.dist-info/top_level.txt
pyxel_config_lab_bridge-0.2.2.dist-info/RECORD
