Metadata-Version: 2.4
Name: pyxel-config-lab-bridge
Version: 0.2.2
Summary: A Python bridge that opens the Pyxel Config Lab UI directly inside Jupyter Notebooks.
Home-page: https://gitlab.com/dobybaxter127/pyxel-config-lab
Author: Doby Baxter
License: MIT
Project-URL: Homepage, https://gitlab.com/dobybaxter127/pyxel-config-lab/-/tree/main/pyxel-config-lab-extension
Project-URL: Source, https://gitlab.com/dobybaxter127/pyxel-config-lab
Project-URL: Issues, https://gitlab.com/dobybaxter127/pyxel-config-lab/-/issues
Requires-Python: >=3.8
Requires-Dist: ipython
Requires-Dist: ipykernel
